smallestenclosingcircle.py
smallestenclosingcircle-0.0.1.dist-info/METADATA
smallestenclosingcircle-0.0.1.dist-info/WHEEL
smallestenclosingcircle-0.0.1.dist-info/top_level.txt
smallestenclosingcircle-0.0.1.dist-info/RECORD
