Metadata-Version: 2.1
Name: smallestenclosingcircle
Version: 0.0.1
Summary: Smallest Enclosing Circle
Home-page: https://github.com/lpasselin/smallestenclosingcircle
License: LGPLv3+
Platform: UNKNOWN
Classifier: Operating System :: OS Independent
Classifier: License :: OSI Approved :: GNU Lesser General Public License v3 or later (LGPLv3+)
Classifier: Programming Language :: Python :: 3
Requires-Python: >=3.4
